gramhopper/__init__.py
gramhopper/bot.py
gramhopper/dict_enum.py
gramhopper/logging_config.py
gramhopper/paths.py
gramhopper/representable.py
gramhopper/users_helper.py
gramhopper/configuration/__init__.py
gramhopper/configuration/boolean_helper.py
gramhopper/configuration/boolean_operators.py
gramhopper/configuration/common_types.py
gramhopper/configuration/rules_parser.py
gramhopper/configuration/rules_parsing_helper.py
gramhopper/configuration/trigger_or_response_params.py
gramhopper/configuration/trigger_or_response_parser.py
gramhopper/handlers/__init__.py
gramhopper/handlers/combined_handlers.py
gramhopper/handlers/default_error_handler.py
gramhopper/handlers/rules_handler.py
gramhopper/responses/__init__.py
gramhopper/responses/basic_responses.py
gramhopper/responses/match_responses.py
gramhopper/responses/preset_responses.py
gramhopper/responses/response_helper.py
gramhopper/responses/responses.py
gramhopper/triggers/__init__.py
gramhopper/triggers/basic_triggers.py
gramhopper/triggers/event_streak_trigger.py
gramhopper/triggers/filter_triggers.py
gramhopper/triggers/text_triggers.py
gramhopper/triggers/trigger_result.py
gramhopper/triggers/triggers.py
gramhopper-3.0.1.dist-info/LICENSE
gramhopper-3.0.1.dist-info/METADATA
gramhopper-3.0.1.dist-info/WHEEL
gramhopper-3.0.1.dist-info/entry_points.txt
gramhopper-3.0.1.dist-info/top_level.txt
gramhopper-3.0.1.dist-info/RECORD
