Metadata-Version: 2.1
Name: gramhopper
Version: 3.0.1
Summary: A bot platform for automatic responses based on various triggers
Home-page: https://github.com/OrBin/gramhopper
Author: Or Bin, Meir Halachmi
Author-email: orbin50@gmail.com, meir.halachmi@gmail.com
License: MIT
Keywords: gramhopper telegram bot
Classifier: Development Status :: 4 - Beta
Classifier: Intended Audience :: End Users/Desktop
Classifier: Intended Audience :: Other Audience
Classifier: License :: OSI Approved :: MIT License
Classifier: Programming Language :: Python :: 3
Classifier: Programming Language :: Python :: 3.10
Classifier: Topic :: Communications :: Chat
License-File: LICENSE
Requires-Dist: python-telegram-bot (==13.15)
Requires-Dist: boolean.py (==3.6)
Requires-Dist: ruamel-yaml (~=0.17)
